daimon/__init__.py
daimon/githf.py
daimon/machina.yaml
daimon-0.0.2.dist-info/LICENSE
daimon-0.0.2.dist-info/METADATA
daimon-0.0.2.dist-info/WHEEL
daimon-0.0.2.dist-info/top_level.txt
daimon-0.0.2.dist-info/RECORD
